ai_sentinel/__init__.py
ai_sentinel/py.typed
ai_sentinel/core/__init__.py
ai_sentinel/core/models.py
ai_sentinel/guards/__init__.py
ai_sentinel/guards/toxicity_guard/__init__.py
ai_sentinel/guards/toxicity_guard/detector.py
ai_sentinel/guards/toxicity_guard/models.py
ai_sentinel/guards/toxicity_guard/prompts.py
ai_sentinel/llm/__init__.py
ai_sentinel/llm/azure_openai.py
ai_sentinel/llm/base.py
ai_sentinel/llm/gemini.py
ai_sentinel/llm/open_source_openai.py
ai_sentinel/llm/transformers_llm.py
ai_sentinel-0.0.10.dist-info/METADATA
ai_sentinel-0.0.10.dist-info/WHEEL
ai_sentinel-0.0.10.dist-info/licenses/LICENSE
ai_sentinel-0.0.10.dist-info/RECORD
