Metadata-Version: 2.4
Name: ai-sentinel
Version: 0.0.10
Summary: Helpful utilities for AI Sentinel toxicity detection
Project-URL: Homepage, https://github.com/reeturajharsh1/ai-sentinel
Project-URL: Repository, https://github.com/reeturajharsh1/ai-sentinel.git
Project-URL: Documentation, https://ai-sentinel.readthedocs.io/
Project-URL: Company, https://www.domyn.com/
Author-email: Althea Masetti Zannini <althea.masettizannini@domyn.com>, Reetu Raj Harsh <reeturaj.harsh@domyn.com>
License-File: LICENSE
Requires-Python: >=3.11
Requires-Dist: google-genai>=1.9.0
Requires-Dist: google-generativeai>=0.8.5
Requires-Dist: jsonschema>=4.25.0
Requires-Dist: myst-parser>=4.0.1
Requires-Dist: nbsphinx>=0.9.7
Requires-Dist: openai>=0.11.5
Requires-Dist: pydantic>=2.11.7
Requires-Dist: python-dotenv>=0.10.2
Requires-Dist: requests>=2.5.4.1
Requires-Dist: transformers>=4.54.1
Requires-Dist: vllm>=0.9.1
